data/__init__.py
data/basic_company_data.csv
sec_downloaders/__init__.py
sec_downloaders/sec_downloaders.py
sec_downloaders-0.4.dist-info/METADATA
sec_downloaders-0.4.dist-info/WHEEL
sec_downloaders-0.4.dist-info/top_level.txt
sec_downloaders-0.4.dist-info/RECORD
